aruco_design/__init__.py
aruco_design/aruco_design.py
aruco_design/command_line.py
aruco_design/extendscript/package.json
aruco_design/extendscript/tsconfig.json
aruco_design/extendscript/webpack.config.js
aruco_design/extendscript/dist/ArucoDesign.js
aruco_design/extendscript/dist/test_arucoMarkerOnPathPoints.js
aruco_design/extendscript/dist/test_countUpPathPoints.js
aruco_design/extendscript/dist/test_element.js
aruco_design/extendscript/dist/test_layer.js
aruco_design/extendscript/dist/test_outputPosition.js
aruco_design/extendscript/src/ArucoDesign.ts
aruco_design/extendscript/src/test_arucoMarkerOnPathPoints.ts
aruco_design/extendscript/src/test_countUpPathPoints.ts
aruco_design/extendscript/src/test_element.ts
aruco_design/extendscript/src/test_layer.ts
aruco_design/extendscript/src/test_outputPosition.ts
aruco_design/extendscript/src/lib/aruco.ts
aruco_design/extendscript/src/lib/io.ts
aruco_design/extendscript/src/lib/position.ts
arucodesign-1.0.dist-info/DESCRIPTION.rst
arucodesign-1.0.dist-info/METADATA
arucodesign-1.0.dist-info/RECORD
arucodesign-1.0.dist-info/WHEEL
arucodesign-1.0.dist-info/entry_points.txt
arucodesign-1.0.dist-info/metadata.json
arucodesign-1.0.dist-info/top_level.txt
